{
  "title": "Loot Sheet NPC 5e (Simple Version)",
  "description": "This module adds an additional NPC sheet which can be used for loot containers such as chests or shopkeepers.",
  "version": "4.1.0",
  "esmodules": [
    "/lootsheet-simple.js"
  ],
  "styles": [
    "/css/lootsheet-simple.css"
  ],
  "socket": true,
  "url": "https://github.com/jopeek/fvtt-loot-sheet-npc-5e",
  "manifest": "https://raw.githubusercontent.com/jopeek/fvtt-loot-sheet-npc-5e/lootsheet-simple/module.json",
  "download": "https://github.com/jopeek/fvtt-loot-sheet-npc-5e/archive/lootsheet-simple.zip",
  "id": "lootsheet-simple",
  "authors": [
    {
      "name": "Jan Ole Peek (ChalkOne), Charles Miller (Kage), NonstickPanda, Kevin Brammer (Striky)",
      "flags": {}
    }
  ],
  "compatibility": {
    "minimum": "10",
    "verified": "10"
  }
}